openqaoa_braket/__init__.py
openqaoa_braket/_version.py
openqaoa_braket/backend_config.py
openqaoa_braket/algorithms/__init__.py
openqaoa_braket/algorithms/jobs/__init__.py
openqaoa_braket/algorithms/jobs/managed_job.py
openqaoa_braket/backends/__init__.py
openqaoa_braket/backends/devices.py
openqaoa_braket/backends/gates_braket.py
openqaoa_braket/backends/qaoa_braket_qpu.py
openqaoa_braket-0.2.6.dist-info/LICENSE
openqaoa_braket-0.2.6.dist-info/METADATA
openqaoa_braket-0.2.6.dist-info/WHEEL
openqaoa_braket-0.2.6.dist-info/entry_points.txt
openqaoa_braket-0.2.6.dist-info/top_level.txt
openqaoa_braket-0.2.6.dist-info/RECORD
